hepdataframe/__init__.py
hepdataframe/hepdataframe.py
hepdataframe/py.typed
hepdataframe-0.1.1.dist-info/LICENSE
hepdataframe-0.1.1.dist-info/WHEEL
hepdataframe-0.1.1.dist-info/METADATA
hepdataframe-0.1.1.dist-info/RECORD
