Metadata-Version: 2.1
Name: hepdataframe
Version: 0.1.1
Summary: HEP Dataframe
Home-page: https://github.com/hepdataframe/hepdataframe
License: BSD-3-Clause
Author: Felipe Silva
Author-email: felipe.silva@cern.ch
Maintainer: Felipe Silva
Maintainer-email: felipe.silva@cern.ch
Requires-Python: >=3.8,<4.0
Classifier: Development Status :: 1 - Planning
Classifier: Intended Audience :: Developers
Classifier: Intended Audience :: Science/Research
Classifier: License :: OSI Approved :: BSD License
Classifier: Operating System :: OS Independent
Classifier: Programming Language :: Python :: 3
Classifier: Programming Language :: Python :: 3.10
Classifier: Programming Language :: Python :: 3.8
Classifier: Programming Language :: Python :: 3.9
Classifier: Topic :: Scientific/Engineering
Provides-Extra: dev
Provides-Extra: docs
Provides-Extra: test
Requires-Dist: awkward (>=1.8.0,<2.0.0)
Requires-Dist: numpy (>=1.22.3,<2.0.0)
Requires-Dist: pytest (>=6); extra == "test" or extra == "dev"
Requires-Dist: sphinx (>=4.0,<5.0); extra == "docs"
Requires-Dist: sphinx_book_theme (>=0.1.0); extra == "docs"
Requires-Dist: sphinx_copybutton (>=0.3.0); extra == "docs"
Requires-Dist: typing_extensions (>=3.7); python_version < "3.8"
Requires-Dist: uproot (>=4.2.2,<5.0.0)
Project-URL: Repository, https://github.com/hepdataframe/hepdataframe
